[1,["1a688d3e1","5azQrDd/lBBKk1NSmhsgRU","f9dmMe2EVB6KyqJCHrJbZp","968V4ETghCC7reYMmNEy4H","beSpX+g1pBI4GaMVnfyzlW","bbO8nEYRZPOpVaeiZyoGub","2edXZI3U9P+bKuBltizKoy"],["_textureSetter","value"],["cc.SpriteFrame",["cc.AnimationClip",["_name","_duration","sample","curveData"],0,11]],[[1,0,1,2,3,4]],[[[{"name":"bomb_effect_08","rect":[985,187,36,40],"offset":[0,8],"originalSize":[36,62],"capInsets":[0,0,0,0]}],[0],0,[0],[0],[0]],[[[0,"common_bomb",0.3,20,[{},"comps",11,[{},"cc.Sprite",11,[{},"spriteFrame",12,[[[{"frame":0},"value",6,0],[{"frame":0.05},"value",6,1],[{"frame":0.1},"value",6,2],[{"frame":0.15},"value",6,3],[{"frame":0.2},"value",6,4],[{"frame":0.25},"value",6,5]],11,11,11,11,11,11]]]]]],0,0,[0,0,0,0,0,0],[1,1,1,1,1,1],[1,2,3,4,5,6]],[[{"name":"bomb_effect_01","rect":[985,275,34,35],"offset":[2.5,4.5],"originalSize":[49,64],"rotated":1,"capInsets":[0,0,0,0]}],[0],0,[0],[0],[0]],[[{"name":"bomb_effect_03","rect":[968,315,53,47],"offset":[2,4.5],"originalSize":[57,64],"capInsets":[0,0,0,0]}],[0],0,[0],[0],[0]],[[{"name":"bomb_effect_05","rect":[601,260,44,52],"offset":[-3.5,4],"originalSize":[51,64],"capInsets":[0,0,0,0]}],[0],0,[0],[0],[0]],[[{"name":"bomb_effect_04","rect":[408,752,51,49],"offset":[0,4.5],"originalSize":[51,64],"rotated":1,"capInsets":[0,0,0,0]}],[0],0,[0],[0],[0]],[[{"name":"bomb_effect_02","rect":[577,752,39,41],"offset":[1.5,4.5],"originalSize":[54,64],"capInsets":[0,0,0,0]}],[0],0,[0],[0],[0]]]]